bakarSecure/__init__.py
bakarSecure-0.2.dist-info/METADATA
bakarSecure-0.2.dist-info/WHEEL
bakarSecure-0.2.dist-info/top_level.txt
bakarSecure-0.2.dist-info/RECORD
