Metadata-Version: 2.1
Name: bakarSecure
Version: 0.2
Summary: This is Abubakar Hafeez  Package
Home-page: https://github.com/AbubakarS989/Bakar-Module
Author: Abubakar Hafeez
Author-email: <abubakarhafeez66@gmail.com>
Classifier: Programming Language :: Python :: 3
Classifier: License :: OSI Approved :: MIT License
Classifier: Operating System :: OS Independent
Requires-Python: >=3.6
